mouths/__init__.py
mouths-0.0.1.dist-info/METADATA
mouths-0.0.1.dist-info/WHEEL
mouths-0.0.1.dist-info/top_level.txt
mouths-0.0.1.dist-info/RECORD
